test/__init__.py
test/fixture_app.py
test/test_wsgiprox.py
wsgiprox/__init__.py
wsgiprox/gevent_ssl.py
wsgiprox/resolvers.py
wsgiprox/wsgiprox.py
wsgiprox-1.5.2.dist-info/DESCRIPTION.rst
wsgiprox-1.5.2.dist-info/METADATA
wsgiprox-1.5.2.dist-info/RECORD
wsgiprox-1.5.2.dist-info/WHEEL
wsgiprox-1.5.2.dist-info/entry_points.txt
wsgiprox-1.5.2.dist-info/metadata.json
wsgiprox-1.5.2.dist-info/top_level.txt
wsgiprox-1.5.2.dist-info/zip-safe
