Metadata-Version: 2.1
Name: wsgiprox
Version: 1.5.2
Summary: HTTP/S proxy with WebSockets over WSGI
Home-page: https://github.com/webrecorder/wsgiprox
Author: Ilya Kreymer
Author-email: ikreymer@gmail.com
License: Apache 2.0
Platform: UNKNOWN
Classifier: Development Status :: 5 - Production/Stable
Classifier: Environment :: Web Environment
Classifier: License :: OSI Approved :: Apache Software License
Classifier: Programming Language :: Python :: 2
Classifier: Programming Language :: Python :: 2.7
Classifier: Programming Language :: Python :: 3
Classifier: Programming Language :: Python :: 3.4
Classifier: Programming Language :: Python :: 3.5
Classifier: Programming Language :: Python :: 3.6
Classifier: Programming Language :: Python :: 3.7
Classifier: Topic :: Software Development :: Libraries :: Python Modules
Classifier: Topic :: Utilities
Provides: wsgiprox
Provides-Extra: gevent-websocket
